cricguru/__init__.py
cricguru/player.py
cricguru/scraper.py
cricguru/team.py
cricguru-2.1.2.dist-info/LICENSE.md
cricguru-2.1.2.dist-info/METADATA
cricguru-2.1.2.dist-info/WHEEL
cricguru-2.1.2.dist-info/RECORD
