Metadata-Version: 2.1
Name: cricguru
Version: 2.1.2
Summary: 
Home-page: https://github.com/puppetmaster12/cricguru
License: MIT
Author: Pavithran
Author-email: pavithranthilakanathan@gmail.com
Requires-Python: >=3.8,<4.0
Classifier: License :: OSI Approved :: MIT License
Classifier: Programming Language :: Python :: 3
Classifier: Programming Language :: Python :: 3.8
Classifier: Programming Language :: Python :: 3.9
Classifier: Programming Language :: Python :: 3.10
Classifier: Programming Language :: Python :: 3.11
Classifier: Programming Language :: Python :: 3.12
Requires-Dist: bs4 (>=0.0.1,<0.0.2)
Requires-Dist: pandas (>=1.5.2,<2.0.0)
Project-URL: Repository, https://github.com/puppetmaster12/cricguru
